lsh/__init__.py
lsh/random_projection.py
lsh/scripts/__init__.py
lsh/scripts/fasttext.py
lsh/tests/__init__.py
lsh/tests/test_lsh.py
lsh_for_indexing-0.0.5.dist-info/LICENSE
lsh_for_indexing-0.0.5.dist-info/METADATA
lsh_for_indexing-0.0.5.dist-info/WHEEL
lsh_for_indexing-0.0.5.dist-info/top_level.txt
lsh_for_indexing-0.0.5.dist-info/RECORD
