Metadata-Version: 2.1
Name: lsh-for-indexing
Version: 0.0.5
Summary: Package for indexing vectors to solr/es
Home-page: https://github.com/helmanofer/lsh-for-indexing
Author: Ofer Helman
Author-email: helmanofer@gmail.com
License: UNKNOWN
Platform: UNKNOWN
Classifier: Programming Language :: Python :: 3
Classifier: License :: OSI Approved :: MIT License
Classifier: Operating System :: OS Independent
Requires-Dist: numpy
Requires-Dist: scipy
Requires-Dist: scikit-learn
